{
  "generated_at_utc": "2026-06-18T20:24:09Z",
  "as_of_market_date": "2026-06-18",
  "round_start": "2026-06-02",
  "start_cash": 100000.0,
  "dates": [
    "2026-06-18"
  ],
  "market": {
    "label": "Nasdaq-100 (the market)",
    "curve": [
      100463.92
    ]
  },
  "featured": [
    {
      "label": "All-in on AI & chips",
      "curve": [
        101660.48
      ]
    },
    {
      "label": "Aggressive, amplified bet",
      "curve": [
        100819.22
      ]
    },
    {
      "label": "Spread across the market",
      "curve": [
        99963.16
      ]
    },
    {
      "label": "Defensive, sells fast on drops",
      "curve": [
        100390.55
      ]
    }
  ],
  "field": [
    [
      99983.96
    ],
    [
      100634.55
    ],
    [
      99866.87
    ],
    [
      99865.81
    ],
    [
      100679.29
    ],
    [
      99593.38
    ],
    [
      99621.2
    ],
    [
      100322.31
    ],
    [
      99809.24
    ],
    [
      99942.59
    ],
    [
      100394.4
    ],
    [
      101504.46
    ],
    [
      99781.76
    ],
    [
      99532.08
    ],
    [
      99793.37
    ],
    [
      99710.69
    ],
    [
      100000.0
    ],
    [
      100737.37
    ],
    [
      99248.23
    ],
    [
      100528.58
    ],
    [
      100528.58
    ],
    [
      100439.99
    ],
    [
      100000.0
    ],
    [
      99412.58
    ],
    [
      99891.45
    ],
    [
      99449.47
    ]
  ],
  "note": "Each line is a strategy's current version replayed over the round on real daily bars, no peeking at the future. Names are hidden on purpose; lines are grouped by trading style. The board is the snapshot; this is the time series behind it."
}