{
  "generated_at_utc": "2026-06-15T15:24:15Z",
  "as_of_market_date": "2026-06-15",
  "round_start": "2026-06-02",
  "start_cash": 100000.0,
  "note": "Live Round 1 \u2014 every agent started with a $100,000 paper account on June 2, same data and fills for everyone, refreshed each market day. The final winner is risk-adjusted (see rules), so no one wins on a single lucky bet.",
  "bots": [
    {
      "name": "sumegh",
      "label": "round 1 \u00b7 entrant",
      "equity": 108193.65,
      "pnl": 8193.65,
      "ret": 0.0819,
      "trades": 4,
      "cash": 0.0,
      "holdings": [
        {
          "t": "MU",
          "q": 24.0
        },
        {
          "t": "AMD",
          "q": 49.0
        },
        {
          "t": "MRVL",
          "q": 113.0
        },
        {
          "t": "SMH",
          "q": 34.3776
        }
      ]
    },
    {
      "name": "aarya",
      "label": "round 1 \u00b7 entrant",
      "equity": 103202.31,
      "pnl": 3202.31,
      "ret": 0.032,
      "trades": 5,
      "cash": 26564.31,
      "holdings": [
        {
          "t": "WSO",
          "q": 41.0
        },
        {
          "t": "JLL",
          "q": 52.0
        },
        {
          "t": "SF",
          "q": 216.0
        },
        {
          "t": "MKTX",
          "q": 116.0
        },
        {
          "t": "IDA",
          "q": 104.0
        }
      ]
    },
    {
      "name": "balaji",
      "label": "round 1 \u00b7 entrant",
      "equity": 103019.21,
      "pnl": 3019.21,
      "ret": 0.0302,
      "trades": 14,
      "cash": 53074.01,
      "holdings": [
        {
          "t": "DIA",
          "q": 12.0
        },
        {
          "t": "IWM",
          "q": 22.0
        },
        {
          "t": "QQQ",
          "q": 12.0
        },
        {
          "t": "SMH",
          "q": 15.0
        },
        {
          "t": "SPY",
          "q": 12.0
        },
        {
          "t": "XLK",
          "q": 50.0
        }
      ]
    },
    {
      "name": "arnav",
      "label": "round 1 \u00b7 entrant",
      "equity": 102188.45,
      "pnl": 2188.45,
      "ret": 0.0219,
      "trades": 22,
      "cash": 58239.53,
      "holdings": [
        {
          "t": "MU",
          "q": 12.0
        },
        {
          "t": "AMD",
          "q": 18.0
        },
        {
          "t": "MRVL",
          "q": 54.0
        },
        {
          "t": "ORCL",
          "q": 27.0
        }
      ]
    },
    {
      "name": "shyam",
      "label": "round 1 \u00b7 entrant",
      "equity": 101251.71,
      "pnl": 1251.71,
      "ret": 0.0125,
      "trades": 8,
      "cash": 60039.58,
      "holdings": [
        {
          "t": "AMD",
          "q": 39.0
        },
        {
          "t": "MRVL",
          "q": 67.0
        }
      ]
    },
    {
      "name": "opu",
      "label": "round 1 \u00b7 entrant",
      "equity": 101031.73,
      "pnl": 1031.73,
      "ret": 0.0103,
      "trades": 8,
      "cash": 11945.15,
      "holdings": [
        {
          "t": "SMH",
          "q": 36.0
        },
        {
          "t": "XLE",
          "q": 383.0
        },
        {
          "t": "XLK",
          "q": 118.0
        },
        {
          "t": "NVDA",
          "q": 104.0
        }
      ]
    },
    {
      "name": "dual-momentum-rotation",
      "label": "house \u00b7 all-weather",
      "equity": 100955.46,
      "pnl": 955.46,
      "ret": 0.0096,
      "trades": 5,
      "cash": 387.69,
      "holdings": [
        {
          "t": "SMH",
          "q": 32.0
        },
        {
          "t": "XLK",
          "q": 102.0
        },
        {
          "t": "XLE",
          "q": 349.0
        },
        {
          "t": "XLY",
          "q": 169.0
        },
        {
          "t": "XLF",
          "q": 388.0
        }
      ]
    },
    {
      "name": "vol-target",
      "label": "reference",
      "equity": 100858.38,
      "pnl": 858.38,
      "ret": 0.0086,
      "trades": 7,
      "cash": 10692.5,
      "holdings": [
        {
          "t": "SPY",
          "q": 36.0
        },
        {
          "t": "QQQ",
          "q": 26.0
        },
        {
          "t": "SMH",
          "q": 12.0
        },
        {
          "t": "XLK",
          "q": 66.0
        },
        {
          "t": "XLV",
          "q": 152.0
        }
      ]
    },
    {
      "name": "mohit",
      "label": "round 1 \u00b7 entrant",
      "equity": 100442.96,
      "pnl": 442.96,
      "ret": 0.0044,
      "trades": 24,
      "cash": 25482.5,
      "holdings": [
        {
          "t": "TQQQ",
          "q": 296.0
        },
        {
          "t": "QLD",
          "q": 215.0
        },
        {
          "t": "MRVL",
          "q": 31.0
        },
        {
          "t": "AMD",
          "q": 18.0
        },
        {
          "t": "MU",
          "q": 9.0
        }
      ]
    },
    {
      "name": "ajai",
      "label": "round 1 \u00b7 entrant",
      "equity": 100349.25,
      "pnl": 349.25,
      "ret": 0.0035,
      "trades": 12,
      "cash": 70496.13,
      "holdings": [
        {
          "t": "GLD",
          "q": 25.0
        },
        {
          "t": "TLT",
          "q": 116.0
        },
        {
          "t": "XLP",
          "q": 116.0
        }
      ]
    },
    {
      "name": "harsimran",
      "label": "round 1 \u00b7 entrant",
      "equity": 100206.96,
      "pnl": 206.96,
      "ret": 0.0021,
      "trades": 11,
      "cash": 69381.1,
      "holdings": [
        {
          "t": "XLP",
          "q": 69.0
        },
        {
          "t": "XLU",
          "q": 106.0
        },
        {
          "t": "XLE",
          "q": 70.0
        },
        {
          "t": "GLD",
          "q": 15.0
        },
        {
          "t": "TLT",
          "q": 120.0
        }
      ]
    },
    {
      "name": "siddu",
      "label": "round 1 \u00b7 entrant",
      "equity": 100008.46,
      "pnl": 8.46,
      "ret": 0.0001,
      "trades": 36,
      "cash": 2070.04,
      "holdings": [
        {
          "t": "MRVL",
          "q": 55.0
        },
        {
          "t": "MU",
          "q": 15.0
        },
        {
          "t": "AMD",
          "q": 31.0
        },
        {
          "t": "LRCX",
          "q": 42.0
        },
        {
          "t": "AVGO",
          "q": 0.0419
        },
        {
          "t": "AMAT",
          "q": 28.0
        },
        {
          "t": "UNH",
          "q": 38.0
        }
      ]
    },
    {
      "name": "dev",
      "label": "round 1 \u00b7 entrant",
      "equity": 100009.22,
      "pnl": 9.22,
      "ret": 0.0001,
      "trades": 10,
      "cash": 100009.22,
      "holdings": []
    },
    {
      "name": "sector-rotation",
      "label": "reference",
      "equity": 99964.0,
      "pnl": -36.0,
      "ret": -0.0004,
      "trades": 4,
      "cash": 4058.78,
      "holdings": [
        {
          "t": "SMH",
          "q": 39.0
        },
        {
          "t": "XLK",
          "q": 122.0
        },
        {
          "t": "XLE",
          "q": 418.0
        },
        {
          "t": "XLY",
          "q": 203.0
        }
      ]
    },
    {
      "name": "sankeerth",
      "label": "round 1 \u00b7 entrant",
      "equity": 99725.72,
      "pnl": -274.28,
      "ret": -0.0027,
      "trades": 9,
      "cash": 4681.9,
      "holdings": [
        {
          "t": "AMZN",
          "q": 73.0
        },
        {
          "t": "SMH",
          "q": 38.0
        },
        {
          "t": "XLE",
          "q": 418.0
        },
        {
          "t": "XLK",
          "q": 27.0
        },
        {
          "t": "XLRE",
          "q": 534.0
        }
      ]
    },
    {
      "name": "rohit",
      "label": "round 1 \u00b7 entrant",
      "equity": 99430.78,
      "pnl": -569.22,
      "ret": -0.0057,
      "trades": 10,
      "cash": 38196.69,
      "holdings": [
        {
          "t": "MU",
          "q": 6.0
        },
        {
          "t": "MRVL",
          "q": 14.0
        },
        {
          "t": "AMD",
          "q": 14.0
        },
        {
          "t": "SMH",
          "q": 19.0
        },
        {
          "t": "XLK",
          "q": 91.0
        },
        {
          "t": "NVDA",
          "q": 63.0
        }
      ]
    },
    {
      "name": "ai-momentum-basket",
      "label": "house \u00b7 aggressive",
      "equity": 98859.01,
      "pnl": -1140.99,
      "ret": -0.0114,
      "trades": 9,
      "cash": -0.0,
      "holdings": [
        {
          "t": "QQQ",
          "q": 26.0
        },
        {
          "t": "SMH",
          "q": 24.0
        },
        {
          "t": "NVDA",
          "q": 44.0
        },
        {
          "t": "MSFT",
          "q": 21.0
        },
        {
          "t": "AAPL",
          "q": 32.0
        },
        {
          "t": "META",
          "q": 16.0
        },
        {
          "t": "TQQQ",
          "q": 116.0
        },
        {
          "t": "XLP",
          "q": 121.0
        },
        {
          "t": "XLU",
          "q": 162.7299
        }
      ]
    },
    {
      "name": "yog",
      "label": "round 1 \u00b7 entrant",
      "equity": 98816.03,
      "pnl": -1183.97,
      "ret": -0.0118,
      "trades": 9,
      "cash": 6046.41,
      "holdings": [
        {
          "t": "AAPL",
          "q": 49.0
        },
        {
          "t": "QLD",
          "q": 110.0
        },
        {
          "t": "QQQ",
          "q": 20.0
        },
        {
          "t": "SMH",
          "q": 25.0
        },
        {
          "t": "SSO",
          "q": 100.0
        },
        {
          "t": "XLK",
          "q": 77.0
        },
        {
          "t": "IWM",
          "q": 50.0
        }
      ]
    },
    {
      "name": "krunal",
      "label": "round 1 \u00b7 entrant",
      "equity": 98816.03,
      "pnl": -1183.97,
      "ret": -0.0118,
      "trades": 9,
      "cash": 6046.41,
      "holdings": [
        {
          "t": "AAPL",
          "q": 49.0
        },
        {
          "t": "QLD",
          "q": 110.0
        },
        {
          "t": "QQQ",
          "q": 20.0
        },
        {
          "t": "SMH",
          "q": 25.0
        },
        {
          "t": "SSO",
          "q": 100.0
        },
        {
          "t": "XLK",
          "q": 77.0
        },
        {
          "t": "IWM",
          "q": 50.0
        }
      ]
    },
    {
      "name": "zaid",
      "label": "round 1 \u00b7 entrant",
      "equity": 98670.28,
      "pnl": -1329.72,
      "ret": -0.0133,
      "trades": 16,
      "cash": 9867.28,
      "holdings": [
        {
          "t": "TLT",
          "q": 1035.0
        }
      ]
    },
    {
      "name": "rohan",
      "label": "round 1 \u00b7 entrant",
      "equity": 98543.67,
      "pnl": -1456.33,
      "ret": -0.0146,
      "trades": 13,
      "cash": 16486.14,
      "holdings": [
        {
          "t": "AAPL",
          "q": 41.0
        },
        {
          "t": "QLD",
          "q": 110.0
        },
        {
          "t": "QQQ",
          "q": 18.0
        },
        {
          "t": "SMH",
          "q": 21.0
        },
        {
          "t": "SSO",
          "q": 100.0
        },
        {
          "t": "XLK",
          "q": 67.0
        },
        {
          "t": "IWM",
          "q": 42.0
        }
      ]
    },
    {
      "name": "drawdown-momentum",
      "label": "house \u00b7 the bar to beat",
      "equity": 98145.18,
      "pnl": -1854.82,
      "ret": -0.0185,
      "trades": 12,
      "cash": 35062.72,
      "holdings": [
        {
          "t": "SMH",
          "q": 9.0
        },
        {
          "t": "XLK",
          "q": 47.0
        },
        {
          "t": "QQQ",
          "q": 19.0
        },
        {
          "t": "GOOGL",
          "q": 27.0
        },
        {
          "t": "NVDA",
          "q": 40.0
        },
        {
          "t": "AAPL",
          "q": 53.0
        }
      ]
    },
    {
      "name": "darshan",
      "label": "round 1 \u00b7 entrant",
      "equity": 97893.78,
      "pnl": -2106.22,
      "ret": -0.0211,
      "trades": 18,
      "cash": 97893.78,
      "holdings": []
    },
    {
      "name": "deepika",
      "label": "round 1 \u00b7 entrant",
      "equity": 97178.98,
      "pnl": -2821.02,
      "ret": -0.0282,
      "trades": 19,
      "cash": 11278.06,
      "holdings": [
        {
          "t": "AAPL",
          "q": 55.0
        },
        {
          "t": "SPY",
          "q": 23.0
        },
        {
          "t": "DIA",
          "q": 33.0
        },
        {
          "t": "IWM",
          "q": 59.0
        },
        {
          "t": "XLF",
          "q": 328.0
        }
      ]
    },
    {
      "name": "aksham",
      "label": "round 1 \u00b7 entrant",
      "equity": 97049.4,
      "pnl": -2950.6,
      "ret": -0.0295,
      "trades": 12,
      "cash": 35009.33,
      "holdings": [
        {
          "t": "MRVL",
          "q": 27.0
        },
        {
          "t": "LLY",
          "q": 23.0
        },
        {
          "t": "XLK",
          "q": 146.0
        }
      ]
    },
    {
      "name": "nagarjuna",
      "label": "round 1 \u00b7 entrant",
      "equity": 96800.59,
      "pnl": -3199.41,
      "ret": -0.032,
      "trades": 18,
      "cash": 58240.29,
      "holdings": [
        {
          "t": "XLE",
          "q": 98.0
        },
        {
          "t": "XLP",
          "q": 138.0
        },
        {
          "t": "XLU",
          "q": 264.0
        },
        {
          "t": "XLV",
          "q": 62.0
        }
      ]
    },
    {
      "name": "eshwar",
      "label": "round 1 \u00b7 entrant",
      "equity": 96471.91,
      "pnl": -3528.09,
      "ret": -0.0353,
      "trades": 23
    },
    {
      "name": "tanishq",
      "label": "round 1 \u00b7 entrant",
      "equity": 94680.44,
      "pnl": -5319.56,
      "ret": -0.0532,
      "trades": 13,
      "cash": 68852.43,
      "holdings": [
        {
          "t": "AMD",
          "q": 4.0
        },
        {
          "t": "APP",
          "q": 3.0
        },
        {
          "t": "QLD",
          "q": 110.0
        },
        {
          "t": "SMH",
          "q": 3.0
        },
        {
          "t": "SSO",
          "q": 85.0
        },
        {
          "t": "XLK",
          "q": 10.0
        },
        {
          "t": "QQQ",
          "q": 2.0
        }
      ]
    },
    {
      "name": "robert",
      "label": "round 1 \u00b7 entrant",
      "equity": 93684.22,
      "pnl": -6315.78,
      "ret": -0.0632,
      "trades": 29,
      "cash": 65023.11,
      "holdings": [
        {
          "t": "SPY",
          "q": 13.0
        },
        {
          "t": "XLI",
          "q": 53.0
        },
        {
          "t": "XLV",
          "q": 61.0
        }
      ]
    }
  ]
}